{
    "sourceFile": "client/src/layout/Footer.jsx",
    "activeCommit": 0,
    "commits": [
        {
            "activePatchIndex": 6,
            "patches": [
                {
                    "date": 1736533313503,
                    "content": "Index: \n===================================================================\n--- \n+++ \n"
                },
                {
                    "date": 1736533363291,
                    "content": "Index: \n===================================================================\n--- \n+++ \n@@ -27,9 +27,9 @@\n         </div>\r\n         \r\n     <div className=\"crm\">\r\n         <div style={{textAlign:'center', marginBottom:'20px'}}>\r\n-        <Link to='' className=\"media-link\" style={{color:'#070C70', marginRight:'10px'}} ><TelegramIcon fontSize=\"large\"/></Link> \r\n+        <Link to='' className=\"media-link\" target=\"_blank\" rel=\"noopener noreferrer\" style={{color:'#070C70', marginRight:'10px'}} ><TelegramIcon fontSize=\"large\"/></Link> \r\n         <Link to='' className=\"media-link\" style={{color:'red', marginRight:'10px'}}><YouTubeIcon fontSize=\"large\"/></Link> \r\n         <Link to='' className=\"media-link\" style={{color:'#6767ff', marginRight:'10px'}}><FacebookIcon fontSize=\"large\"/></Link>\r\n         <Link to='https://twitter.com/okin_tech' className=\"media-link\" style={{color:'#070C70'}} ><XIcon  fontSize=\"large\"/></Link> \r\n         </div>\r\n"
                },
                {
                    "date": 1736533370280,
                    "content": "Index: \n===================================================================\n--- \n+++ \n@@ -0,0 +1,44 @@\n+import '../css/layout.css';\r\n+import okinLogo from \"/assets/Okinlm.svg\"\r\n+import TelegramIcon from '@mui/icons-material/Telegram';\r\n+import XIcon from '@mui/icons-material/X';\r\n+import YouTubeIcon from '@mui/icons-material/YouTube';\r\n+import FacebookIcon from '@mui/icons-material/Facebook';\r\n+import {Link} from \"react-router-dom\";\r\n+\r\n+\r\n+\r\n+const Footer = () => {\r\n+    const year = new Date().getFullYear()\r\n+\r\n+    return (\r\n+<>\r\n+\r\n+\r\n+<footer style={{backgroundColor:'white'}}>  \r\n+    <hr/>\r\n+            \r\n+  <img src={okinLogo} alt=\"okinLogo\" className='okinLogo' />\r\n+\r\n+    <div className=\"grid\" style={{display:'flex', justifyContent:'center'}}>\r\n+   <Link className=\"footer-link\"  style={{color:\"#070C70\"}} to=\"/about\" >About</Link>\r\n+   <Link className=\"footer-link\" style={{color:\"#070C70\"}} to=\"/privacy-policy\" >Privacy Policy</Link> \r\n+   <Link className=\"footer-link\" style={{color:\"#070C70\"}} to=\"/login\" >Login</Link> \r\n+        </div>\r\n+        \r\n+    <div className=\"crm\">\r\n+        <div style={{textAlign:'center', marginBottom:'20px'}}>\r\n+        <Link to='' className=\"media-link\" target=\"_blank\" rel=\"noopener noreferrer\" style={{color:'#070C70', marginRight:'10px'}} ><TelegramIcon fontSize=\"large\"/></Link> \r\n+        <Link to='' className=\"media-link\" target=\"_blank\" rel=\"noopener noreferrer\" style={{color:'red', marginRight:'10px'}}><YouTubeIcon fontSize=\"large\"/></Link> \r\n+        <Link to='' className=\"media-link\"  style={{color:'#6767ff', marginRight:'10px'}}><FacebookIcon fontSize=\"large\"/></Link>\r\n+        <Link to='https://twitter.com/okin_tech' className=\"media-link\" style={{color:'#070C70'}} ><XIcon  fontSize=\"large\"/></Link> \r\n+        </div>\r\n+    </div>\r\n+    \r\n+      <Link href=\"https://okin.onrender.com/\" style={{color:\"#070C70\"}} className=\"footer-link\" >&copy; {year} CodeX - All Rights Reserved | Ọkín technologies</Link> \r\n+      </footer> \r\n+</>\r\n+    )\r\n+}\r\n+\r\n+export default Footer;\n\\ No newline at end of file\n"
                },
                {
                    "date": 1736533376254,
                    "content": "Index: \n===================================================================\n--- \n+++ \n@@ -0,0 +1,44 @@\n+import '../css/layout.css';\r\n+import okinLogo from \"/assets/Okinlm.svg\"\r\n+import TelegramIcon from '@mui/icons-material/Telegram';\r\n+import XIcon from '@mui/icons-material/X';\r\n+import YouTubeIcon from '@mui/icons-material/YouTube';\r\n+import FacebookIcon from '@mui/icons-material/Facebook';\r\n+import {Link} from \"react-router-dom\";\r\n+\r\n+\r\n+\r\n+const Footer = () => {\r\n+    const year = new Date().getFullYear()\r\n+\r\n+    return (\r\n+<>\r\n+\r\n+\r\n+<footer style={{backgroundColor:'white'}}>  \r\n+    <hr/>\r\n+            \r\n+  <img src={okinLogo} alt=\"okinLogo\" className='okinLogo' />\r\n+\r\n+    <div className=\"grid\" style={{display:'flex', justifyContent:'center'}}>\r\n+   <Link className=\"footer-link\"  style={{color:\"#070C70\"}} to=\"/about\" >About</Link>\r\n+   <Link className=\"footer-link\" style={{color:\"#070C70\"}} to=\"/privacy-policy\" >Privacy Policy</Link> \r\n+   <Link className=\"footer-link\" style={{color:\"#070C70\"}} to=\"/login\" >Login</Link> \r\n+        </div>\r\n+        \r\n+    <div className=\"crm\">\r\n+        <div style={{textAlign:'center', marginBottom:'20px'}}>\r\n+        <Link to='' className=\"media-link\" target=\"_blank\" rel=\"noopener noreferrer\" style={{color:'#070C70', marginRight:'10px'}} ><TelegramIcon fontSize=\"large\"/></Link> \r\n+        <Link to='' className=\"media-link\" target=\"_blank\" rel=\"noopener noreferrer\" style={{color:'red', marginRight:'10px'}}><YouTubeIcon fontSize=\"large\"/></Link> \r\n+        <Link to='' className=\"media-link\" target=\"_blank\" rel=\"noopener noreferrer\" style={{color:'#6767ff', marginRight:'10px'}}><FacebookIcon fontSize=\"large\"/></Link>\r\n+        <Link to='https://twitter.com/okin_tech' target=\"_blank\" rel=\"noopener noreferrer\" className=\"media-link\" style={{color:'#070C70'}} ><XIcon  fontSize=\"large\"/></Link> \r\n+        </div>\r\n+    </div>\r\n+    \r\n+      <Link href=\"https://okin.onrender.com/\" style={{color:\"#070C70\"}} className=\"footer-link\" >&copy; {year} CodeX - All Rights Reserved | Ọkín technologies</Link> \r\n+      </footer> \r\n+</>\r\n+    )\r\n+}\r\n+\r\n+export default Footer;\n\\ No newline at end of file\n"
                },
                {
                    "date": 1736533411817,
                    "content": "Index: \n===================================================================\n--- \n+++ \n@@ -0,0 +1,44 @@\n+import '../css/layout.css';\r\n+import okinLogo from \"/assets/Okinlm.svg\"\r\n+import TelegramIcon from '@mui/icons-material/Telegram';\r\n+import XIcon from '@mui/icons-material/X';\r\n+import YouTubeIcon from '@mui/icons-material/YouTube';\r\n+import FacebookIcon from '@mui/icons-material/Facebook';\r\n+import {Link} from \"react-router-dom\";\r\n+\r\n+\r\n+\r\n+const Footer = () => {\r\n+    const year = new Date().getFullYear()\r\n+\r\n+    return (\r\n+<>\r\n+\r\n+\r\n+<footer style={{backgroundColor:'white'}}>  \r\n+    <hr/>\r\n+            \r\n+  <img src={okinLogo} alt=\"okinLogo\" className='okinLogo' />\r\n+\r\n+    <div className=\"grid\" style={{display:'flex', justifyContent:'center'}}>\r\n+   <Link className=\"footer-link\"  style={{color:\"#070C70\"}} to=\"/about\" >About</Link>\r\n+   <Link className=\"footer-link\" style={{color:\"#070C70\"}} to=\"/privacy-policy\" >Privacy Policy</Link> \r\n+   <Link className=\"footer-link\" style={{color:\"#070C70\"}} to=\"/login\" >Login</Link> \r\n+        </div>\r\n+        \r\n+    <div className=\"crm\">\r\n+        <div style={{textAlign:'center', marginBottom:'20px'}}>\r\n+        <Link to='' className=\"media-link\" target=\"_blank\" rel=\"noopener noreferrer\" style={{color:'#070C70', marginRight:'10px'}} ><TelegramIcon fontSize=\"large\"/></Link> \r\n+        <Link to='' className=\"media-link\" target=\"_blank\" rel=\"noopener noreferrer\" style={{color:'red', marginRight:'10px'}}><YouTubeIcon fontSize=\"large\"/></Link> \r\n+        <Link to='' className=\"media-link\" target=\"_blank\" rel=\"noopener noreferrer\" style={{color:'#6767ff', marginRight:'10px'}}><FacebookIcon fontSize=\"large\"/></Link>\r\n+        <Link to='https://twitter.com/okin_tech' target=\"_blank\" rel=\"noopener noreferrer\" className=\"media-link\" style={{color:'#070C70'}} ><XIcon  fontSize=\"large\"/></Link> \r\n+        </div>\r\n+    </div>\r\n+    \r\n+      <Link href=\"\" target=\"_blank\" rel=\"noopener noreferrer\" style={{color:\"#070C70\"}} className=\"footer-link\" >&copy; {year} CodeX - All Rights Reserved | Ọkín technologies</Link> \r\n+      </footer> \r\n+</>\r\n+    )\r\n+}\r\n+\r\n+export default Footer;\n\\ No newline at end of file\n"
                },
                {
                    "date": 1736534097780,
                    "content": "Index: \n===================================================================\n--- \n+++ \n@@ -30,9 +30,9 @@\n         <div style={{textAlign:'center', marginBottom:'20px'}}>\r\n         <Link to='' className=\"media-link\" target=\"_blank\" rel=\"noopener noreferrer\" style={{color:'#070C70', marginRight:'10px'}} ><TelegramIcon fontSize=\"large\"/></Link> \r\n         <Link to='' className=\"media-link\" target=\"_blank\" rel=\"noopener noreferrer\" style={{color:'red', marginRight:'10px'}}><YouTubeIcon fontSize=\"large\"/></Link> \r\n         <Link to='' className=\"media-link\" target=\"_blank\" rel=\"noopener noreferrer\" style={{color:'#6767ff', marginRight:'10px'}}><FacebookIcon fontSize=\"large\"/></Link>\r\n-        <Link to='' target=\"_blank\" rel=\"noopener noreferrer\" className=\"media-link\" style={{color:'#070C70'}} ><XIcon  fontSize=\"large\"/></Link> \r\n+        <Link to='https://x.com/okintechnologie' target=\"_blank\" rel=\"noopener noreferrer\" className=\"media-link\" style={{color:'#070C70'}} ><XIcon  fontSize=\"large\"/></Link> \r\n         </div>\r\n     </div>\r\n     \r\n       <Link href=\"https://okin.onrender.com/\" target=\"_blank\" rel=\"noopener noreferrer\" style={{color:\"#070C70\"}} className=\"footer-link\" >&copy; {year} CodeX - All Rights Reserved | Ọkín technologies</Link> \r\n"
                },
                {
                    "date": 1736534119934,
                    "content": "Index: \n===================================================================\n--- \n+++ \n@@ -0,0 +1,44 @@\n+import '../css/layout.css';\r\n+import okinLogo from \"/assets/Okinlm.svg\"\r\n+import TelegramIcon from '@mui/icons-material/Telegram';\r\n+import XIcon from '@mui/icons-material/X';\r\n+import YouTubeIcon from '@mui/icons-material/YouTube';\r\n+import FacebookIcon from '@mui/icons-material/Facebook';\r\n+import {Link} from \"react-router-dom\";\r\n+\r\n+\r\n+\r\n+const Footer = () => {\r\n+    const year = new Date().getFullYear()\r\n+\r\n+    return (\r\n+<>\r\n+\r\n+\r\n+<footer style={{backgroundColor:'white'}}>  \r\n+    <hr/>\r\n+            \r\n+  <img src={okinLogo} alt=\"okinLogo\" className='okinLogo' />\r\n+\r\n+    <div className=\"grid\" style={{display:'flex', justifyContent:'center'}}>\r\n+   <Link className=\"footer-link\"  style={{color:\"#070C70\"}} to=\"/about\" >About</Link>\r\n+   <Link className=\"footer-link\" style={{color:\"#070C70\"}} to=\"/privacy-policy\" >Privacy Policy</Link> \r\n+   <Link className=\"footer-link\" style={{color:\"#070C70\"}} to=\"/login\" >Login</Link> \r\n+        </div>\r\n+        \r\n+    <div className=\"crm\">\r\n+        <div style={{textAlign:'center', marginBottom:'20px'}}>\r\n+        <Link to='' className=\"media-link\" target=\"_blank\" rel=\"noopener noreferrer\" style={{color:'#070C70', marginRight:'10px'}} ><TelegramIcon fontSize=\"large\"/></Link> \r\n+        <Link to='' className=\"media-link\" target=\"_blank\" rel=\"noopener noreferrer\" style={{color:'red', marginRight:'10px'}}><YouTubeIcon fontSize=\"large\"/></Link> \r\n+        <Link to='https://web.facebook.com/okintechnologies/' className=\"media-link\" target=\"_blank\" rel=\"noopener noreferrer\" style={{color:'#6767ff', marginRight:'10px'}}><FacebookIcon fontSize=\"large\"/></Link>\r\n+        <Link to='https://x.com/okintechnologie' target=\"_blank\" rel=\"noopener noreferrer\" className=\"media-link\" style={{color:'#070C70'}} ><XIcon  fontSize=\"large\"/></Link> \r\n+        </div>\r\n+    </div>\r\n+    \r\n+      <Link href=\"https://okin.onrender.com/\" target=\"_blank\" rel=\"noopener noreferrer\" style={{color:\"#070C70\"}} className=\"footer-link\" >&copy; {year} CodeX - All Rights Reserved | Ọkín technologies</Link> \r\n+      </footer> \r\n+</>\r\n+    )\r\n+}\r\n+\r\n+export default Footer;\n\\ No newline at end of file\n"
                }
            ],
            "date": 1736533313503,
            "name": "Commit-0",
            "content": "import '../css/layout.css';\r\nimport okinLogo from \"/assets/Okinlm.svg\"\r\nimport TelegramIcon from '@mui/icons-material/Telegram';\r\nimport XIcon from '@mui/icons-material/X';\r\nimport YouTubeIcon from '@mui/icons-material/YouTube';\r\nimport FacebookIcon from '@mui/icons-material/Facebook';\r\nimport {Link} from \"react-router-dom\";\r\n\r\n\r\n\r\nconst Footer = () => {\r\n    const year = new Date().getFullYear()\r\n\r\n    return (\r\n<>\r\n\r\n\r\n<footer style={{backgroundColor:'white'}}>  \r\n    <hr/>\r\n            \r\n  <img src={okinLogo} alt=\"okinLogo\" className='okinLogo' />\r\n\r\n    <div className=\"grid\" style={{display:'flex', justifyContent:'center'}}>\r\n   <Link className=\"footer-link\"  style={{color:\"#070C70\"}} to=\"/about\" >About</Link>\r\n   <Link className=\"footer-link\" style={{color:\"#070C70\"}} to=\"/privacy-policy\" >Privacy Policy</Link> \r\n   <Link className=\"footer-link\" style={{color:\"#070C70\"}} to=\"/login\" >Login</Link> \r\n        </div>\r\n        \r\n    <div className=\"crm\">\r\n        <div style={{textAlign:'center', marginBottom:'20px'}}>\r\n        <Link to='' className=\"media-link\" style={{color:'#070C70', marginRight:'10px'}} ><TelegramIcon fontSize=\"large\"/></Link> \r\n        <Link to='' className=\"media-link\" style={{color:'red', marginRight:'10px'}}><YouTubeIcon fontSize=\"large\"/></Link> \r\n        <Link to='' className=\"media-link\" style={{color:'#6767ff', marginRight:'10px'}}><FacebookIcon fontSize=\"large\"/></Link>\r\n        <Link to='https://twitter.com/okin_tech' className=\"media-link\" style={{color:'#070C70'}} ><XIcon  fontSize=\"large\"/></Link> \r\n        </div>\r\n    </div>\r\n    \r\n      <Link href=\"https://okin.onrender.com/\" style={{color:\"#070C70\"}} className=\"footer-link\" >&copy; {year} CodeX - All Rights Reserved | Ọkín technologies</Link> \r\n      </footer> \r\n</>\r\n    )\r\n}\r\n\r\nexport default Footer;"
        }
    ]
}